{
    "el": {
        "τίτλος": "Ρήδοπας",
        "reedops": "Γένος Ρήδοπας (Reedops)",	
        "reedops-περιγραφή-1": "",
        

        "reedops-reedops_maurulus": "Ρήδοπας ο μαυρίσκος",
        
        "gallery": [
            
        ]
    },

    "en": {
        "τίτλος": "Reedops",
        "reedops": "Genus Reedops",
        "reedops-περιγραφή-1": "",

        "reedops-reedops_maurulus": "Reedops maurulus",
        
        "gallery": [
            
        ]
    },

    "grc": {
        "τίτλος": "Ῥηδόψ",
        "reedops": "Γένος Ῥηδόψ (Reedops)",
        "reedops-περιγραφή-1": "",

        "reedops-reedops_maurulus": "Ῥηδόψ ὁ μαυρίσκος",
        
        "gallery": [
            
        ]
    }
}
